[
  {
    "氏名": "石本　亮三",
    "登録名": "石本　亮三",
    "よみ": "いしもと　りょうぞう",
    "X（旧Twitter）": "https://x.com/IshimotoRyozo",
    "所属": "立憲リベラルの会"
  },
  {
    "氏名": "末吉　美帆子",
    "登録名": "末吉　美帆子",
    "よみ": "すえよし　みほこ",
    "X（旧Twitter）": "https://x.com/sueyoshimihoko",
    "所属": "立憲リベラルの会"
  },
  {
    "氏名": "斉藤　かおり",
    "登録名": "斉藤　かおり",
    "よみ": "さいとう　かおり",
    "X（旧Twitter）": "https://x.com/kaori_sansei",
    "所属": "自由民主党・維新・参政・無所属の会"
  },
  {
    "氏名": "長岡　恵子",
    "登録名": "長岡　恵子",
    "よみ": "ながおか　けいこ",
    "X（旧Twitter）": "https://x.com/keiko12nagaoka",
    "所属": "立憲民主党・れいわ新選組"
  },
  {
    "氏名": "赤川　洋二",
    "登録名": "赤川　洋二",
    "よみ": "あかがわ　ようじ",
    "X（旧Twitter）": "https://x.com/akagawayoji",
    "所属": "立憲民主党・れいわ新選組"
  },
  {
    "氏名": "神戸　鉄郎",
    "登録名": "神戸　鉄郎",
    "よみ": "かんべ　てつろう",
    "X（旧Twitter）": "https://x.com/tokorozawakambe",
    "所属": "自由民主党・維新・参政・無所属の会"
  },
  {
    "氏名": "小林　澄子",
    "登録名": "小林　澄子",
    "よみ": "こばやし　すみこ",
    "X（旧Twitter）": null,
    "所属": "日本共産党"
  },
  {
    "氏名": "中井　めぐみ",
    "登録名": "中井　めぐみ",
    "よみ": "なかい　めぐみ",
    "X（旧Twitter）": "https://x.com/mn_jcptokoro",
    "所属": "日本共産党"
  },
  {
    "氏名": "花岡　健太",
    "登録名": "花岡　健太",
    "よみ": "はなおか　けんた",
    "X（旧Twitter）": "https://x.com/hanaoka_jcptoko",
    "所属": "日本共産党"
  },
  {
    "氏名": "矢作　いづみ",
    "登録名": "矢作　いづみ",
    "よみ": "やさく　いづみ",
    "X（旧Twitter）": "https://x.com/q6vtalztbo9x3ph",
    "所属": "日本共産党"
  },
  {
    "氏名": "島田　一隆",
    "登録名": "島田　一隆",
    "よみ": "しまだ　かずたか",
    "X（旧Twitter）": "https://x.com/shimada_moai",
    "所属": "さきがけ"
  },
  {
    "氏名": "長谷川　礼奈",
    "登録名": "長谷川　礼奈",
    "よみ": "はせがわ　りな",
    "X（旧Twitter）": "https://x.com/hasegawarina812",
    "所属": "さきがけ"
  },
  {
    "氏名": "荻野　泰男",
    "登録名": "荻野　泰男",
    "よみ": "おぎの　やすお",
    "X（旧Twitter）": "https://x.com/oginoyasuo/",
    "所属": "さきがけ"
  },
  {
    "氏名": "植竹　成年",
    "登録名": "植竹　成年",
    "よみ": "うえたけ　なりとし",
    "X（旧Twitter）": null,
    "所属": "公明党"
  },
  {
    "氏名": "大久保　竜一",
    "登録名": "大久保　竜一",
    "よみ": "おおくぼ　りゅういち",
    "X（旧Twitter）": "https://x.com/okuboryuichi",
    "所属": "公明党"
  },
  {
    "氏名": "川辺　浩直",
    "登録名": "川辺　浩直",
    "よみ": "かわべ　ひろなお",
    "X（旧Twitter）": "https://x.com/hiriho1",
    "所属": "公明党"
  },
  {
    "氏名": "松本　明信",
    "登録名": "松本　明信",
    "よみ": "まつもと　あきのぶ",
    "X（旧Twitter）": "https://x.com/smile_matsumoto",
    "所属": "市民クラブ未来"
  },
  {
    "氏名": "粕谷　不二夫",
    "登録名": "粕谷　不二夫",
    "よみ": "かすや　ふじお",
    "X（旧Twitter）": "https://x.com/f_kasuya",
    "所属": "市民クラブ未来"
  },
  {
    "氏名": "佐野　允彦",
    "登録名": "佐野　允彦",
    "よみ": "さの　みつひこ",
    "X（旧Twitter）": "https://x.com/ms06241983",
    "所属": "自由民主党・維新・参政・無所属の会"
  },
  {
    "氏名": "大庭　祥照",
    "登録名": "大庭　祥照",
    "よみ": "おおば　よしてる",
    "X（旧Twitter）": null,
    "所属": "自由民主党・維新・参政・無所属の会"
  },
  {
    "氏名": "前田　浩昭",
    "登録名": "前田　浩昭",
    "よみ": "まえだ　ひろあき",
    "X（旧Twitter）": "https://x.com/maechin916",
    "所属": "自由民主党・維新・参政・無所属の会"
  },
  {
    "氏名": "谷口　雅典",
    "登録名": "谷口　雅典",
    "よみ": "たにぐち　まさのり",
    "X（旧Twitter）": "https://x.com/taniguchi1965",
    "所属": "至誠自民クラブ"
  },
  {
    "氏名": "大石　健一",
    "登録名": "大石　健一",
    "よみ": "おおいし　けんいち",
    "X（旧Twitter）": null,
    "所属": "至誠自民クラブ"
  },
  {
    "氏名": "亀山　恭子",
    "登録名": "亀山　恭子",
    "よみ": "かめやま　きょうこ",
    "X（旧Twitter）": "https://x.com/kameyamakyoko",
    "所属": "公明党"
  },
  {
    "氏名": "山口　浩美",
    "登録名": "山口　浩美",
    "よみ": "やまぐち　ひろみ",
    "X（旧Twitter）": null,
    "所属": "公明党"
  },
  {
    "氏名": "福原　浩昭",
    "登録名": "福原　浩昭",
    "よみ": "ふくはら　ひろあき",
    "X（旧Twitter）": "https://x.com/fukuharahiroaki",
    "所属": "公明党"
  },
  {
    "氏名": "中　毅志",
    "登録名": "中　毅志",
    "よみ": "なか　たけし",
    "X（旧Twitter）": null,
    "所属": "市民クラブ未来"
  },
  {
    "氏名": "青木　利幸",
    "登録名": "青木　利幸",
    "よみ": "あおき　としゆき",
    "X（旧Twitter）": null,
    "所属": "市民クラブ未来"
  },
  {
    "氏名": "入沢　豊",
    "登録名": "入沢　豊",
    "よみ": "いりさわ　ゆたか",
    "X（旧Twitter）": "https://x.com/irisawa_yutaka",
    "所属": "自由民主党・維新・参政・無所属の会"
  },
  {
    "氏名": "石原　昂",
    "登録名": "石原　昂",
    "よみ": "いしはら　たかし",
    "X（旧Twitter）": "https://x.com/ishiharatakash3",
    "所属": "自由民主党・維新・参政・無所属の会"
  },
  {
    "氏名": "大舘　隆行",
    "登録名": "大舘　隆行",
    "よみ": "おおだち　たかゆき",
    "X（旧Twitter）": null,
    "所属": "至誠自民クラブ"
  },
  {
    "氏名": "秋田　孝",
    "登録名": "秋田　孝",
    "よみ": "あきた　たかし",
    "X（旧Twitter）": null,
    "所属": "至誠自民クラブ"
  },
  {
    "氏名": "斎藤　由紀",
    "登録名": "斎藤　由紀",
    "よみ": "さいとう　ゆき",
    "X（旧Twitter）": "https://x.com/tokorozawakaze",
    "所属": "至誠自民クラブ"
  }
]